{"detailsUrl":"/g/d/Brick_Out/index.html","name":"Brick Out","id":"51","iconUrl":"https://games.lernong.com/Brick_Out/icon.png","playUrl":"/g/p/Brick_Out/index.html","gameUrl":"https://games.lernong.com/g/p/Brick_Out/game.html","products":["com.lrbib.brick_out.bundle_one","com.lrbib.brick_out.bundle_two","com.lrbib.brick_out.bundle_three","com.lrbib.brick_out.bundle_four","com.lrbib.brick_out.bundle_five","com.lrbib.brick_out.bundle_six"],"subscriptions":["com.lrbib.brick_out.trial","com.lrbib.brick_out.weekly","com.lrbib.brick_out.monthly","com.lrbib.brick_out.three_months","com.lrbib.brick_out.six_months"]}