{"detailsUrl":"/g/d/vidmate_Candy_Car_Escape/index.html","name":"vidmate Candy Car Escape","id":"179","iconUrl":"https://games.lernong.com/vidmate_Candy_Car_Escape/icon.png","playUrl":"/g/p/vidmate_Candy_Car_Escape/index.html","gameUrl":"https://games.lernong.com/g/p/vidmate_Candy_Car_Escape/game.html","products":["com.hmhxy.vidmate_candy_car_escape.trial","com.hmhxy.vidmate_candy_car_escape.weekly","com.hmhxy.vidmate_candy_car_escape.monthly","com.hmhxy.vidmate_candy_car_escape.three_months","com.hmhxy.vidmate_candy_car_escape.six_months"]}